{
	"description": "项目配置文件",
	"packOptions": {
		"ignore": []
	},
	"setting": {
		"urlCheck": false,
		"es6": true,
		"postcss": true,
		"minified": true,
		"newFeature": true,
		"coverView": true,
		"autoAudits": false,
		"checkInvalidKey": true,
		"checkSiteMap": true,
		"uploadWithSourceMap": true,
		"babelSetting": {
			"ignore": [],
			"disablePlugins": [],
			"outputPath": ""
		}
	},
	"compileType": "miniprogram",
	"libVersion": "2.11.0",
	"appid": "wx22b234012b6f1fb2",
	"projectname": "fangchan1",
	"debugOptions": {
		"hidedInDevtools": []
	},
	"isGameTourist": false,
	"simulatorType": "wechat",
	"simulatorPluginLibVersion": {},
	"condition": {
		"search": {
			"current": -1,
			"list": []
		},
		"conversation": {
			"current": -1,
			"list": []
		},
		"plugin": {
			"current": -1,
			"list": []
		},
		"game": {
			"currentL": -1,
			"list": []
		},
		"gamePlugin": {
			"current": -1,
			"list": []
		},
		"miniprogram": {
			"current": -1,
			"list": [
				{
					"id": -1,
					"name": "pages/active/index",
					"pathName": "pages/active/index",
					"query": "",
					"scene": null
				},
				{
					"id": -1,
					"name": "pages/list/index",
					"pathName": "pages/list/index",
					"query": "",
					"scene": null
				},
				{
					"id": -1,
					"name": "pages/user/index",
					"pathName": "pages/user/index",
					"query": "",
					"scene": null
				},
				{
					"id": -1,
					"name": "pages/myCollection/index",
					"pathName": "pages/myCollection/index",
					"query": "",
					"scene": null
				},
				{
					"id": -1,
					"name": "pages/articleDetail/index",
					"pathName": "pages/articleDetail/index",
					"query": "",
					"scene": null
				},
				{
					"id": -1,
					"name": "pages/activeDetail/index",
					"pathName": "pages/activeDetail/index",
					"query": "",
					"scene": null
				},
				{
					"id": -1,
					"name": "pages/recommend/index",
					"pathName": "pages/recommend/index",
					"query": "",
					"scene": null
				},
				{
					"id": -1,
					"name": "pages/housingPrice/index",
					"pathName": "pages/housingPrice/index",
					"query": "",
					"scene": null
				},
				{
					"id": -1,
					"name": "pages/housingDetail/index",
					"pathName": "pages/housingDetail/index",
					"query": "",
					"scene": null
				},
				{
					"id": -1,
					"name": "pages/aboutUs/index",
					"pathName": "pages/aboutUs/index",
					"query": "",
					"scene": null
				},
				{
					"id": -1,
					"name": "pages/cooperation/index",
					"pathName": "pages/cooperation/index",
					"query": "",
					"scene": null
				},
				{
					"id": -1,
					"name": "pages/leavingMessage/index",
					"pathName": "pages/leavingMessage/index",
					"query": "",
					"scene": null
				},
				{
					"id": -1,
					"name": "pages/recommendedList/index",
					"pathName": "pages/recommendedList/index",
					"scene": null
				}
			]
		}
	}
}